claude_wt/__init__.py
claude_wt/cli.py
claude_wt-0.2.0.dist-info/METADATA
claude_wt-0.2.0.dist-info/WHEEL
claude_wt-0.2.0.dist-info/entry_points.txt
claude_wt-0.2.0.dist-info/RECORD
