Metadata-Version: 2.4
Name: claude-wt
Version: 0.2.0
Summary: Utility for running Claude Code in parallel and managing dedicated git worktrees.
Project-URL: Homepage, https://github.com/jlowin/claude-wt
Author: Jeremiah Lowin
Keywords: ai,claude,git
Classifier: Development Status :: 4 - Beta
Classifier: Intended Audience :: Developers
Classifier: Programming Language :: Python :: 3
Requires-Python: >=3.12
Requires-Dist: rich>=13.0.0
Requires-Dist: typer>=0.16.0
